llama_factory_recorder/__init__.py
llama_factory_recorder/main.py
llama_factory_recorder-0.4.1.dist-info/METADATA
llama_factory_recorder-0.4.1.dist-info/WHEEL
llama_factory_recorder-0.4.1.dist-info/entry_points.txt
llama_factory_recorder-0.4.1.dist-info/top_level.txt
llama_factory_recorder-0.4.1.dist-info/RECORD
