Metadata-Version: 2.4
Name: llama-factory-recorder
Version: 0.4.1
Summary: Dora Node for VLM
Author-email: Haixuan Xavier Tao <tao.xavier@outlook.com>, Enzo Le Van <dev@enzo-le-van.fr>
Requires-Python: >=3.8
Requires-Dist: dora-rs>=0.3.9
Requires-Dist: pillow>=10.4.0
Requires-Dist: opencv-python>=4.1.1
